netmri_bootstrap/__init__.py
netmri_bootstrap/config.json.in
netmri_bootstrap/config.py
netmri_bootstrap/dryrun.py
netmri_bootstrap/webui_broker.py
netmri_bootstrap/objects/__init__.py
netmri_bootstrap/objects/api.py
netmri_bootstrap/objects/git.py
netmri_bootstrap-0.0.3.data/scripts/netmri-bootstrap.py
tests/__init__.py
tests/test_api.py
tests/test_config.py
tests/test_git.py
tests/test_netmri-bootstrap.py
tests/test_script_metadata.py
netmri_bootstrap-0.0.3.dist-info/AUTHORS.rst
netmri_bootstrap-0.0.3.dist-info/LICENSE
netmri_bootstrap-0.0.3.dist-info/METADATA
netmri_bootstrap-0.0.3.dist-info/WHEEL
netmri_bootstrap-0.0.3.dist-info/top_level.txt
netmri_bootstrap-0.0.3.dist-info/RECORD
