Metadata-Version: 2.1
Name: netmri-bootstrap
Version: 0.0.3
Summary: Bootstrapper for interaction with NetMRI
Home-page: https://github.com/infobloxopen/netmri-bootstrap
Author: Ingmar Van Glabbeek
Author-email: ingmar@infoblox.com
License: Apache
Keywords: netmri-bootstrap
Platform: UNKNOWN
Classifier: Development Status :: 2 - Pre-Alpha
Classifier: Intended Audience :: Developers
Classifier: License :: OSI Approved :: Apache Software License
Classifier: Natural Language :: English
Classifier: Programming Language :: Python :: 3
Classifier: Programming Language :: Python :: 3.7
Classifier: Programming Language :: Python :: 3.8
Classifier: Programming Language :: Python :: 3.9
Requires-Dist: requests (>=2.5.2)
Requires-Dist: urllib3 (>=1.13)
Requires-Dist: setuptools (>=17.1)
Requires-Dist: six (>=1.10)
Requires-Dist: wheel (>=0.33)
Requires-Dist: lxml (>=4.5.0)
Requires-Dist: gitpython (>=3.1.2)
Requires-Dist: infoblox-netmri (>=3.7.0.0)
